LICENSE
poisson_disc.py
poisson_disc-0.2.0.dist-info/LICENSE
poisson_disc-0.2.0.dist-info/WHEEL
poisson_disc-0.2.0.dist-info/METADATA
poisson_disc-0.2.0.dist-info/RECORD
